pysandra/__about__.py
pysandra/__init__.py
pysandra/client.py
pysandra/codecs.py
pysandra/connection.py
pysandra/constants.py
pysandra/core.py
pysandra/dispatcher.py
pysandra/exceptions.py
pysandra/messages.py
pysandra/protocol.py
pysandra/types.py
pysandra/utils.py
pysandra/v4protocol.py
pysandra-0.4.0.dist-info/LICENSE-APACHE
pysandra-0.4.0.dist-info/LICENSE-MIT
pysandra-0.4.0.dist-info/METADATA
pysandra-0.4.0.dist-info/WHEEL
pysandra-0.4.0.dist-info/top_level.txt
pysandra-0.4.0.dist-info/RECORD
