Metadata-Version: 2.1
Name: pysandra
Version: 0.4.0
Summary: Python driver for Cassandra focusing on asyncio users (INCOMPLETE).
Home-page: https://github.com/toppk/pysandra
Author: Kenneth Topp
Author-email: toppk@bllue.org
License: MIT or Apache License, Version 2.0
Platform: UNKNOWN
Classifier: Development Status :: 3 - Alpha
Classifier: Intended Audience :: Developers
Classifier: License :: OSI Approved :: Apache Software License
Classifier: License :: OSI Approved :: MIT License
Classifier: Operating System :: OS Independent
Classifier: Topic :: Software Development :: Libraries :: Python Modules
Classifier: Framework :: AsyncIO
Classifier: Programming Language :: Python :: 3.6
Classifier: Programming Language :: Python :: 3.7
Classifier: Programming Language :: Python :: 3.8
Requires-Python: >=3.6
Provides-Extra: compression
Requires-Dist: python-snappy ; extra == 'compression'
Requires-Dist: lz4 ; extra == 'compression'
Provides-Extra: docs
Requires-Dist: mkdocs ; extra == 'docs'
Requires-Dist: mkdocs-material ; extra == 'docs'
Requires-Dist: mkautodoc ; extra == 'docs'
Requires-Dist: snakefood3 ; extra == 'docs'
